mend_sca_cleanup_tool/__init__.py
mend_sca_cleanup_tool/_version.py
mend_sca_cleanup_tool/sca_cleanup_tool.py
ws_cleanup_tool-24.6.4.dist-info/LICENSE
ws_cleanup_tool-24.6.4.dist-info/METADATA
ws_cleanup_tool-24.6.4.dist-info/WHEEL
ws_cleanup_tool-24.6.4.dist-info/entry_points.txt
ws_cleanup_tool-24.6.4.dist-info/top_level.txt
ws_cleanup_tool-24.6.4.dist-info/RECORD
